LICENSE
qottoauth/__init__.py
qottoauth/api/__init__.py
qottoauth/api/base.py
qottoauth/api/cached.py
qottoauth/api/gql.py
qottoauth/api/test.py
qottoauth/models.py
qottoauth/py.typed
qottoauth/service.py
qotto_auth_client-2.2.4.dist-info/LICENSE
qotto_auth_client-2.2.4.dist-info/METADATA
qotto_auth_client-2.2.4.dist-info/WHEEL
qotto_auth_client-2.2.4.dist-info/RECORD
