Metadata-Version: 2.1
Name: qotto-auth-client
Version: 2.2.4
Summary: Qotto/QottoAuthClient
Author: Qotto Dev Team
Author-email: dev@qotto.net
Requires-Python: >=3.7,<4.0
Classifier: Programming Language :: Python :: 3
Classifier: Programming Language :: Python :: 3.7
Classifier: Programming Language :: Python :: 3.8
Classifier: Programming Language :: Python :: 3.9
Classifier: Programming Language :: Python :: 3.10
Classifier: Programming Language :: Python :: 3.11
Requires-Dist: PyJWT (>=2.0.0)
Requires-Dist: cryptography (>=37.0.0)
Requires-Dist: eventy (>=3.3.0)
Requires-Dist: gql[requests] (>=2.0.0)
Requires-Dist: requests (>=2.0.0)
